DevWorksDjangoLib/__init__.py
DevWorksDjangoLib/_version.py
DevWorksDjangoLib/settings.py
devworks_commands_helpers/__init__.py
devworks_commands_helpers/db_nuke.py
devworks_commands_helpers/logging_struct.py
devworks_django/ForceLogout.py
devworks_django/PasswordChange.py
devworks_django/__init__.py
devworks_django/model.py
devworks_drf/__init__.py
devworks_drf/form_field_errors.py
devworks_drf/oidc.py
devworks_drf/pagination.py
devworks_drf/viewset.py
devworks_drf/permission/__init__.py
devworks_drf/permission/drf_permissions.py
devworks_hydra/__init__.py
devworks_hydra/rest.py
devworks_mail/AdminEncryptEmailBackend.py
devworks_mail/__init__.py
devworks_mail/mail.py
devworksdjangolib-0.0.3.dist-info/METADATA
devworksdjangolib-0.0.3.dist-info/WHEEL
devworksdjangolib-0.0.3.dist-info/entry_points.txt
devworksdjangolib-0.0.3.dist-info/top_level.txt
devworksdjangolib-0.0.3.dist-info/RECORD
