Metadata-Version: 2.4
Name: DevWorksDjangoLib
Version: 0.0.3
Summary: DevWorks Django Library
Author-email: Sambor Czarski <sam.czarski@gmail.com>
Requires-Dist: pydash
